[ {
  "sha" : "b73b3174a54703007003270a73c839421cbbfa73",
  "commit" : {
    "author" : {
      "name" : "yanTingwww",
      "email" : "839693121@qq.com",
      "date" : "2015-11-03T01:36:28Z"
    },
    "committer" : {
      "name" : "yanTingwww",
      "email" : "839693121@qq.com",
      "date" : "2015-11-03T01:36:28Z"
    },
    "message" : "实验四修改",
    "tree" : {
      "sha" : "a5445e4c2f4a5f4bb21695e02cde620ec4a285a5",
      "url" : "https://api.github.com/repos/hzuapps/angular-erp-ui/git/trees/a5445e4c2f4a5f4bb21695e02cde620ec4a285a5"
    },
    "url" : "https://api.github.com/repos/hzuapps/angular-erp-ui/git/commits/b73b3174a54703007003270a73c839421cbbfa73",
    "comment_count" : 0
  },
  "url" : "https://api.github.com/repos/hzuapps/angular-erp-ui/commits/b73b3174a54703007003270a73c839421cbbfa73",
  "html_url" : "https://github.com/hzuapps/angular-erp-ui/commit/b73b3174a54703007003270a73c839421cbbfa73",
  "comments_url" : "https://api.github.com/repos/hzuapps/angular-erp-ui/commits/b73b3174a54703007003270a73c839421cbbfa73/comments",
  "author" : {
    "login" : "yanTingwww",
    "id" : 15097619,
    "avatar_url" : "https://avatars.githubusercontent.com/u/15097619?v=3",
    "gravatar_id" : "",
    "url" : "https://api.github.com/users/yanTingwww",
    "html_url" : "https://github.com/yanTingwww",
    "followers_url" : "https://api.github.com/users/yanTingwww/followers",
    "following_url" : "https://api.github.com/users/yanTingwww/following{/other_user}",
    "gists_url" : "https://api.github.com/users/yanTingwww/gists{/gist_id}",
    "starred_url" : "https://api.github.com/users/yanTingwww/starred{/owner}{/repo}",
    "subscriptions_url" : "https://api.github.com/users/yanTingwww/subscriptions",
    "organizations_url" : "https://api.github.com/users/yanTingwww/orgs",
    "repos_url" : "https://api.github.com/users/yanTingwww/repos",
    "events_url" : "https://api.github.com/users/yanTingwww/events{/privacy}",
    "received_events_url" : "https://api.github.com/users/yanTingwww/received_events",
    "type" : "User",
    "site_admin" : false
  },
  "committer" : {
    "login" : "yanTingwww",
    "id" : 15097619,
    "avatar_url" : "https://avatars.githubusercontent.com/u/15097619?v=3",
    "gravatar_id" : "",
    "url" : "https://api.github.com/users/yanTingwww",
    "html_url" : "https://github.com/yanTingwww",
    "followers_url" : "https://api.github.com/users/yanTingwww/followers",
    "following_url" : "https://api.github.com/users/yanTingwww/following{/other_user}",
    "gists_url" : "https://api.github.com/users/yanTingwww/gists{/gist_id}",
    "starred_url" : "https://api.github.com/users/yanTingwww/starred{/owner}{/repo}",
    "subscriptions_url" : "https://api.github.com/users/yanTingwww/subscriptions",
    "organizations_url" : "https://api.github.com/users/yanTingwww/orgs",
    "repos_url" : "https://api.github.com/users/yanTingwww/repos",
    "events_url" : "https://api.github.com/users/yanTingwww/events{/privacy}",
    "received_events_url" : "https://api.github.com/users/yanTingwww/received_events",
    "type" : "User",
    "site_admin" : false
  },
  "parents" : [ {
    "sha" : "bc6bbcd28144906d792242e30e4430b5a6af4939",
    "url" : "https://api.github.com/repos/hzuapps/angular-erp-ui/commits/bc6bbcd28144906d792242e30e4430b5a6af4939",
    "html_url" : "https://github.com/hzuapps/angular-erp-ui/commit/bc6bbcd28144906d792242e30e4430b5a6af4939"
  } ]
} ]