[ {
  "sha" : "9697ce4616e1522ec6a3e2e24490c45abf171f6b",
  "commit" : {
    "author" : {
      "name" : "LIMITAYANG",
      "email" : "962401409@qq.com",
      "date" : "2016-12-04T08:44:05Z"
    },
    "committer" : {
      "name" : "LIMITAYANG",
      "email" : "962401409@qq.com",
      "date" : "2016-12-04T08:44:05Z"
    },
    "message" : "#4 提交实验代码",
    "tree" : {
      "sha" : "9a690c5d07d2495e2d4ab95ffb8fb093db0223e6",
      "url" : "https://api.github.com/repos/hzuapps/java-web/git/trees/9a690c5d07d2495e2d4ab95ffb8fb093db0223e6"
    },
    "url" : "https://api.github.com/repos/hzuapps/java-web/git/commits/9697ce4616e1522ec6a3e2e24490c45abf171f6b",
    "comment_count" : 0
  },
  "url" : "https://api.github.com/repos/hzuapps/java-web/commits/9697ce4616e1522ec6a3e2e24490c45abf171f6b",
  "html_url" : "https://github.com/hzuapps/java-web/commit/9697ce4616e1522ec6a3e2e24490c45abf171f6b",
  "comments_url" : "https://api.github.com/repos/hzuapps/java-web/commits/9697ce4616e1522ec6a3e2e24490c45abf171f6b/comments",
  "author" : {
    "login" : "LIMITAYANG",
    "id" : 22512059,
    "avatar_url" : "https://avatars.githubusercontent.com/u/22512059?v=3",
    "gravatar_id" : "",
    "url" : "https://api.github.com/users/LIMITAYANG",
    "html_url" : "https://github.com/LIMITAYANG",
    "followers_url" : "https://api.github.com/users/LIMITAYANG/followers",
    "following_url" : "https://api.github.com/users/LIMITAYANG/following{/other_user}",
    "gists_url" : "https://api.github.com/users/LIMITAYANG/gists{/gist_id}",
    "starred_url" : "https://api.github.com/users/LIMITAYANG/starred{/owner}{/repo}",
    "subscriptions_url" : "https://api.github.com/users/LIMITAYANG/subscriptions",
    "organizations_url" : "https://api.github.com/users/LIMITAYANG/orgs",
    "repos_url" : "https://api.github.com/users/LIMITAYANG/repos",
    "events_url" : "https://api.github.com/users/LIMITAYANG/events{/privacy}",
    "received_events_url" : "https://api.github.com/users/LIMITAYANG/received_events",
    "type" : "User",
    "site_admin" : false
  },
  "committer" : {
    "login" : "LIMITAYANG",
    "id" : 22512059,
    "avatar_url" : "https://avatars.githubusercontent.com/u/22512059?v=3",
    "gravatar_id" : "",
    "url" : "https://api.github.com/users/LIMITAYANG",
    "html_url" : "https://github.com/LIMITAYANG",
    "followers_url" : "https://api.github.com/users/LIMITAYANG/followers",
    "following_url" : "https://api.github.com/users/LIMITAYANG/following{/other_user}",
    "gists_url" : "https://api.github.com/users/LIMITAYANG/gists{/gist_id}",
    "starred_url" : "https://api.github.com/users/LIMITAYANG/starred{/owner}{/repo}",
    "subscriptions_url" : "https://api.github.com/users/LIMITAYANG/subscriptions",
    "organizations_url" : "https://api.github.com/users/LIMITAYANG/orgs",
    "repos_url" : "https://api.github.com/users/LIMITAYANG/repos",
    "events_url" : "https://api.github.com/users/LIMITAYANG/events{/privacy}",
    "received_events_url" : "https://api.github.com/users/LIMITAYANG/received_events",
    "type" : "User",
    "site_admin" : false
  },
  "parents" : [ {
    "sha" : "f1317fbca8572becc0aa20cf2a6e5aaa1aa14454",
    "url" : "https://api.github.com/repos/hzuapps/java-web/commits/f1317fbca8572becc0aa20cf2a6e5aaa1aa14454",
    "html_url" : "https://github.com/hzuapps/java-web/commit/f1317fbca8572becc0aa20cf2a6e5aaa1aa14454"
  } ]
}, {
  "sha" : "73962a075616501c49798b0da960da646f8f1044",
  "commit" : {
    "author" : {
      "name" : "LIMITAYANG",
      "email" : "962401409@qq.com",
      "date" : "2016-12-04T08:59:21Z"
    },
    "committer" : {
      "name" : "LIMITAYANG",
      "email" : "962401409@qq.com",
      "date" : "2016-12-04T08:59:21Z"
    },
    "message" : "#5 提交实验代码",
    "tree" : {
      "sha" : "c13707506aafa3fbbf46cd2716cd9a1cba6df270",
      "url" : "https://api.github.com/repos/hzuapps/java-web/git/trees/c13707506aafa3fbbf46cd2716cd9a1cba6df270"
    },
    "url" : "https://api.github.com/repos/hzuapps/java-web/git/commits/73962a075616501c49798b0da960da646f8f1044",
    "comment_count" : 0
  },
  "url" : "https://api.github.com/repos/hzuapps/java-web/commits/73962a075616501c49798b0da960da646f8f1044",
  "html_url" : "https://github.com/hzuapps/java-web/commit/73962a075616501c49798b0da960da646f8f1044",
  "comments_url" : "https://api.github.com/repos/hzuapps/java-web/commits/73962a075616501c49798b0da960da646f8f1044/comments",
  "author" : {
    "login" : "LIMITAYANG",
    "id" : 22512059,
    "avatar_url" : "https://avatars.githubusercontent.com/u/22512059?v=3",
    "gravatar_id" : "",
    "url" : "https://api.github.com/users/LIMITAYANG",
    "html_url" : "https://github.com/LIMITAYANG",
    "followers_url" : "https://api.github.com/users/LIMITAYANG/followers",
    "following_url" : "https://api.github.com/users/LIMITAYANG/following{/other_user}",
    "gists_url" : "https://api.github.com/users/LIMITAYANG/gists{/gist_id}",
    "starred_url" : "https://api.github.com/users/LIMITAYANG/starred{/owner}{/repo}",
    "subscriptions_url" : "https://api.github.com/users/LIMITAYANG/subscriptions",
    "organizations_url" : "https://api.github.com/users/LIMITAYANG/orgs",
    "repos_url" : "https://api.github.com/users/LIMITAYANG/repos",
    "events_url" : "https://api.github.com/users/LIMITAYANG/events{/privacy}",
    "received_events_url" : "https://api.github.com/users/LIMITAYANG/received_events",
    "type" : "User",
    "site_admin" : false
  },
  "committer" : {
    "login" : "LIMITAYANG",
    "id" : 22512059,
    "avatar_url" : "https://avatars.githubusercontent.com/u/22512059?v=3",
    "gravatar_id" : "",
    "url" : "https://api.github.com/users/LIMITAYANG",
    "html_url" : "https://github.com/LIMITAYANG",
    "followers_url" : "https://api.github.com/users/LIMITAYANG/followers",
    "following_url" : "https://api.github.com/users/LIMITAYANG/following{/other_user}",
    "gists_url" : "https://api.github.com/users/LIMITAYANG/gists{/gist_id}",
    "starred_url" : "https://api.github.com/users/LIMITAYANG/starred{/owner}{/repo}",
    "subscriptions_url" : "https://api.github.com/users/LIMITAYANG/subscriptions",
    "organizations_url" : "https://api.github.com/users/LIMITAYANG/orgs",
    "repos_url" : "https://api.github.com/users/LIMITAYANG/repos",
    "events_url" : "https://api.github.com/users/LIMITAYANG/events{/privacy}",
    "received_events_url" : "https://api.github.com/users/LIMITAYANG/received_events",
    "type" : "User",
    "site_admin" : false
  },
  "parents" : [ {
    "sha" : "9697ce4616e1522ec6a3e2e24490c45abf171f6b",
    "url" : "https://api.github.com/repos/hzuapps/java-web/commits/9697ce4616e1522ec6a3e2e24490c45abf171f6b",
    "html_url" : "https://github.com/hzuapps/java-web/commit/9697ce4616e1522ec6a3e2e24490c45abf171f6b"
  } ]
} ]