{
  "committer" : {
    "login" : "fanslead",
    "id" : 22066473,
    "avatar_url" : "https://avatars.githubusercontent.com/u/22066473?v=3",
    "gravatar_id" : "",
    "url" : "https://api.github.com/users/fanslead",
    "html_url" : "https://github.com/fanslead",
    "followers_url" : "https://api.github.com/users/fanslead/followers",
    "following_url" : "https://api.github.com/users/fanslead/following{/other_user}",
    "gists_url" : "https://api.github.com/users/fanslead/gists{/gist_id}",
    "starred_url" : "https://api.github.com/users/fanslead/starred{/owner}{/repo}",
    "subscriptions_url" : "https://api.github.com/users/fanslead/subscriptions",
    "organizations_url" : "https://api.github.com/users/fanslead/orgs",
    "repos_url" : "https://api.github.com/users/fanslead/repos",
    "events_url" : "https://api.github.com/users/fanslead/events{/privacy}",
    "received_events_url" : "https://api.github.com/users/fanslead/received_events",
    "type" : "User",
    "site_admin" : false
  },
  "stats" : {
    "total" : 29,
    "additions" : 0,
    "deletions" : 29
  },
  "author" : {
    "login" : "fanslead",
    "id" : 22066473,
    "avatar_url" : "https://avatars.githubusercontent.com/u/22066473?v=3",
    "gravatar_id" : "",
    "url" : "https://api.github.com/users/fanslead",
    "html_url" : "https://github.com/fanslead",
    "followers_url" : "https://api.github.com/users/fanslead/followers",
    "following_url" : "https://api.github.com/users/fanslead/following{/other_user}",
    "gists_url" : "https://api.github.com/users/fanslead/gists{/gist_id}",
    "starred_url" : "https://api.github.com/users/fanslead/starred{/owner}{/repo}",
    "subscriptions_url" : "https://api.github.com/users/fanslead/subscriptions",
    "organizations_url" : "https://api.github.com/users/fanslead/orgs",
    "repos_url" : "https://api.github.com/users/fanslead/repos",
    "events_url" : "https://api.github.com/users/fanslead/events{/privacy}",
    "received_events_url" : "https://api.github.com/users/fanslead/received_events",
    "type" : "User",
    "site_admin" : false
  },
  "html_url" : "https://github.com/hzuapps/java-web/commit/8a51c34cea43f992f11f1b5f5698630ec639a82e",
  "commit" : {
    "author" : {
      "name" : "fanslead",
      "email" : "136590076@qq.com",
      "date" : "2016-10-22T05:13:04Z"
    },
    "committer" : {
      "name" : "fanslead",
      "email" : "136590076@qq.com",
      "date" : "2016-10-22T05:13:04Z"
    },
    "message" : "#3 提交实验代码",
    "tree" : {
      "sha" : "c2e6d8bbd397ec1381d56d8ee6cca3a233882011",
      "url" : "https://api.github.com/repos/hzuapps/java-web/git/trees/c2e6d8bbd397ec1381d56d8ee6cca3a233882011"
    },
    "url" : "https://api.github.com/repos/hzuapps/java-web/git/commits/8a51c34cea43f992f11f1b5f5698630ec639a82e",
    "comment_count" : 0
  },
  "comments_url" : "https://api.github.com/repos/hzuapps/java-web/commits/8a51c34cea43f992f11f1b5f5698630ec639a82e/comments",
  "files" : [ {
    "sha" : "e44f8ede82e93030bb7ab9ee5d7f9e8eb1c28580",
    "filename" : "labs/1414080902120/index.html",
    "status" : "removed",
    "additions" : 0,
    "deletions" : 29,
    "changes" : 29,
    "blob_url" : "https://github.com/hzuapps/java-web/blob/c2fb878dc841d475388ba8b616282ef44a63dd08/labs/1414080902120/index.html",
    "raw_url" : "https://github.com/hzuapps/java-web/raw/c2fb878dc841d475388ba8b616282ef44a63dd08/labs/1414080902120/index.html",
    "contents_url" : "https://api.github.com/repos/hzuapps/java-web/contents/labs/1414080902120/index.html?ref=c2fb878dc841d475388ba8b616282ef44a63dd08",
    "patch" : "@@ -1,29 +0,0 @@\n-<!DOCTYPE html>\n-<html lang=\"en\">\n-<head>\n-\t<!-- useless -->\n-\t<title>最代码分享解析Json数据的HTML5音乐播放器</title>\n-\t<meta http-equiv=\"Content-Type\" content=\"text/html;charset=UTF-8\">\n-\t<link rel=\"stylesheet\" href=\"junk/readme.css\" type=\"text/css\" media=\"screen\">\n-\n-\t<script type=\"text/javascript\" src=\"js/jquery.min.js\"></script>\n-\t<script type=\"text/javascript\" src=\"js/speakker-big.js\"></script>\n-\t<script type=\"text/javascript\">\n-\t$(document).ready(function() {\n-\t\tprojekktor('.projekktor');\n-\t});\n-\t</script>\n-    \n-</head>\n-<body>\n-\n-\t<div id=\"wrap\">\n-\t\t<div class=\"inside\">\n-\t\t\t<audio class=\"projekktor speakker dark\">\n-\t\t\t\t<source src=\"js/playlist.js\" type=\"application/json\"/>\n-\t\t\t</audio>\n-\t\t</div>\n-\t</div>\n-\t<script type=\"text/javascript\" src=\"junk/noise.js\"></script>\n-</body>\n-</html>"
  } ],
  "sha" : "8a51c34cea43f992f11f1b5f5698630ec639a82e",
  "url" : "https://api.github.com/repos/hzuapps/java-web/commits/8a51c34cea43f992f11f1b5f5698630ec639a82e",
  "parents" : [ {
    "sha" : "c2fb878dc841d475388ba8b616282ef44a63dd08",
    "url" : "https://api.github.com/repos/hzuapps/java-web/commits/c2fb878dc841d475388ba8b616282ef44a63dd08",
    "html_url" : "https://github.com/hzuapps/java-web/commit/c2fb878dc841d475388ba8b616282ef44a63dd08"
  } ]
}