{
  "committer" : {
    "login" : "jiushig",
    "id" : 22068297,
    "avatar_url" : "https://avatars.githubusercontent.com/u/22068297?v=3",
    "gravatar_id" : "",
    "url" : "https://api.github.com/users/jiushig",
    "html_url" : "https://github.com/jiushig",
    "followers_url" : "https://api.github.com/users/jiushig/followers",
    "following_url" : "https://api.github.com/users/jiushig/following{/other_user}",
    "gists_url" : "https://api.github.com/users/jiushig/gists{/gist_id}",
    "starred_url" : "https://api.github.com/users/jiushig/starred{/owner}{/repo}",
    "subscriptions_url" : "https://api.github.com/users/jiushig/subscriptions",
    "organizations_url" : "https://api.github.com/users/jiushig/orgs",
    "repos_url" : "https://api.github.com/users/jiushig/repos",
    "events_url" : "https://api.github.com/users/jiushig/events{/privacy}",
    "received_events_url" : "https://api.github.com/users/jiushig/received_events",
    "type" : "User",
    "site_admin" : false
  },
  "stats" : {
    "total" : 178,
    "additions" : 178,
    "deletions" : 0
  },
  "author" : {
    "login" : "jiushig",
    "id" : 22068297,
    "avatar_url" : "https://avatars.githubusercontent.com/u/22068297?v=3",
    "gravatar_id" : "",
    "url" : "https://api.github.com/users/jiushig",
    "html_url" : "https://github.com/jiushig",
    "followers_url" : "https://api.github.com/users/jiushig/followers",
    "following_url" : "https://api.github.com/users/jiushig/following{/other_user}",
    "gists_url" : "https://api.github.com/users/jiushig/gists{/gist_id}",
    "starred_url" : "https://api.github.com/users/jiushig/starred{/owner}{/repo}",
    "subscriptions_url" : "https://api.github.com/users/jiushig/subscriptions",
    "organizations_url" : "https://api.github.com/users/jiushig/orgs",
    "repos_url" : "https://api.github.com/users/jiushig/repos",
    "events_url" : "https://api.github.com/users/jiushig/events{/privacy}",
    "received_events_url" : "https://api.github.com/users/jiushig/received_events",
    "type" : "User",
    "site_admin" : false
  },
  "html_url" : "https://github.com/hzuapps/java-web/commit/934e003eb507dc9457a49a03e994d83b6efdf18f",
  "commit" : {
    "author" : {
      "name" : "jiushig",
      "email" : "3300939642@qq.com",
      "date" : "2016-10-21T02:28:21Z"
    },
    "committer" : {
      "name" : "jiushig",
      "email" : "3300939642@qq.com",
      "date" : "2016-10-21T02:28:21Z"
    },
    "message" : "#3 提交实验代码",
    "tree" : {
      "sha" : "4555051ee739a849c4f37e47fef46a6f43dec558",
      "url" : "https://api.github.com/repos/hzuapps/java-web/git/trees/4555051ee739a849c4f37e47fef46a6f43dec558"
    },
    "url" : "https://api.github.com/repos/hzuapps/java-web/git/commits/934e003eb507dc9457a49a03e994d83b6efdf18f",
    "comment_count" : 0
  },
  "comments_url" : "https://api.github.com/repos/hzuapps/java-web/commits/934e003eb507dc9457a49a03e994d83b6efdf18f/comments",
  "files" : [ {
    "sha" : "7eefe73bbf1a1298839953a1daff6846904d2bd7",
    "filename" : "labs/1414080902139/index.jsp",
    "status" : "added",
    "additions" : 138,
    "deletions" : 0,
    "changes" : 138,
    "blob_url" : "https://github.com/hzuapps/java-web/blob/934e003eb507dc9457a49a03e994d83b6efdf18f/labs/1414080902139/index.jsp",
    "raw_url" : "https://github.com/hzuapps/java-web/raw/934e003eb507dc9457a49a03e994d83b6efdf18f/labs/1414080902139/index.jsp",
    "contents_url" : "https://api.github.com/repos/hzuapps/java-web/contents/labs/1414080902139/index.jsp?ref=934e003eb507dc9457a49a03e994d83b6efdf18f",
    "patch" : "@@ -0,0 +1,138 @@\n+<%@ page language=\"java\" import=\"java.util.*\" pageEncoding=\"UTF-8\"%>\n+<%\n+String path = request.getContextPath();\n+String basePath = request.getScheme()+\"://\"+request.getServerName()+\":\"+request.getServerPort()+path+\"/\";\n+%>\n+\n+<!DOCTYPE HTML PUBLIC \"-//W3C//DTD HTML 4.01 Transitional//EN\">\n+<html>\n+  <head>\n+    <base href=\"<%=basePath%>\">\n+    \n+    <title>Add Your Resume</title>\n+\t<meta http-equiv=\"pragma\" content=\"no-cache\">\n+\t<meta http-equiv=\"cache-control\" content=\"no-cache\">\n+\t<meta http-equiv=\"expires\" content=\"0\">    \n+\t<meta http-equiv=\"keywords\" content=\"keyword1,keyword2,keyword3\">\n+\t<meta http-equiv=\"description\" content=\"This is my page\">\n+\t<!--\n+\t<link rel=\"stylesheet\" type=\"text/css\" href=\"styles.css\">\n+\t-->\n+\t<link rel=\"stylesheet\" href=\"http://cdn.bootcss.com/bootstrap/3.3.0/css/bootstrap.min.css\">\n+\t<!-- HTML5 shim and Respond.js for IE8 support of HTML5 elements and media queries -->\n+    <!-- WARNING: Respond.js doesn't work if you view the page via file:// -->\n+    <!--[if lt IE 9]>\n+      \t<script src=\"http://cdn.bootcss.com/html5shiv/3.7.2/html5shiv.min.js\"></script>\n+      \t<script src=\"http://cdn.bootcss.com/respond.js/1.4.2/respond.min.js\"></script>\n+    <![endif]-->\n+\t<style type=\"text/css\">\n+\t\t.headline{\n+\t\t\tpadding-right: 0;\n+\t\t\tpadding-left: 0;\n+\t\t\tbackground-color:#5bc0de;\n+\t\t\tmargin-top:0;\n+\t\t\tmargin-bottom: 15px;\n+\t\t\theight: 45px;\n+\t\t\tline-height: 45px;\n+\t\t\tfont-size: 24px;\n+\t\t\tcolor: #ffffff\n+\t\t}\n+\t</style>\n+  </head>\n+  \n+ <body>\n+ <div class=\"container\">\n+\t<form id=\"target\" class=\"form-horizontal\" role=\"form\" action=\"inforeceive.jsp\" mothod=\"post\" style=\"background-color: #f5f5f5;margin-bottom:0\">\n+\t<!-- headline -->\n+\t<div class=\"headline text-center\">Add Your Resume</div>\n+\t<!-- Name -->\n+\t<div class=\"form-group\">\n+    \t<label for=\"FullName\" class=\"col-sm-2 col-sm-offset-2 control-label text-nowrap\">Full Name</label>\n+    \t<div class=\"col-sm-5\">\n+      \t\t<input type=\"text\" name=\"fullnameinfo\" class=\"form-control\" id=\"\" placeholder=\"Full Name\">\n+    \t</div>\t\n+    </div>\n+    <!-- Sex -->\n+\t<div class=\"form-group\">\n+\t\t<label for=\"Sex\" class=\"col-sm-2 col-sm-offset-2 control-label\">Sex</label>\n+    \t<div class=\"col-sm-5\" >\n+    \t\t<select class=\"form-control\" name=\"sexinfo\">\n+    \t\t\t<option value=\"Male\">Male</option>\n+    \t\t\t<option value=\"Female\">Female</option>\n+    \t\t</select>\n+    \t</div>\n+   \t<!-- Grade --> \t\t\n+  \t</div>\n+  \t<div class=\"form-group\">\n+  \t\t<label for=\"Grade\" class=\"col-sm-2 col-sm-offset-2 control-label\">Grade</label>\n+    \t<div class=\"col-sm-5\">\n+      \t\t<select class=\"form-control\">\n+    \t\t\t<option value=\"Freshman\">Freshman</option>\n+    \t\t\t<option value=\"Sophomore\">Sophomore</option>\n+    \t\t\t<option value=\"Junior\">Junior</option>\n+    \t\t\t<option value=\"Senior\">Senior</option>\n+    \t\t\t<option value=\"Graduate\">Graduate</option>\n+    \t\t</select>\n+    \t</div>\n+  \t</div>\n+  \t<!-- Profession -->\n+  \t<div class=\"form-group\">\n+  \t\t<label for=\"Profession\" class=\"col-sm-2 col-sm-offset-2 control-label\">Profession</label>\n+    \t<div class=\"col-sm-5\">\n+      \t\t<input type=\"text\" class=\"form-control\" id=\"Profession\" placeholder=\"Profession\">\n+    \t</div>\n+  \t</div>\n+  \t<!-- Tel -->\n+  \t<div class=\"form-group\">\n+  \t\t<label for=\"Tel\" class=\"col-sm-2 col-sm-offset-2 control-label\">Tel</label>\n+    \t<div class=\"col-sm-5\">\n+      \t\t<input type=\"tel\" class=\"form-control\" id=\"Tel\" placeholder=\"Telephone Number\">\n+    \t</div>\n+  \t</div>\n+  \t<!-- Email -->\n+  \t<div class=\"form-group\">\n+  \t\t<label for=\"\" class=\"col-sm-2 col-sm-offset-2 control-label\">Email</label>\n+    \t<div class=\"col-sm-5\">\n+      \t\t<input type=\"email\" class=\"form-control\" id=\"email\" placeholder=\"Email\">\n+    \t</div>\n+  \t</div>\n+  \t<!-- Hobby -->\n+  \t<div class=\"form-group\">\n+  \t\t<label for=\"hobby\" class=\"col-sm-2 col-sm-offset-2 control-label\">Hobby</label>\n+    \t<div class=\"col-sm-5\">\n+      \t\t<textarea class=\"form-control\" id=\"hobby\"></textarea>\n+    \t</div>\n+  \t</div>\n+  \t<!-- Speciality -->\n+  \t<div class=\"form-group\">\n+  \t\t<label for=\"\" class=\"col-sm-2 col-sm-offset-2 control-label\">Speciality</label>\n+    \t<div class=\"col-sm-5\">\n+      \t\t<textarea class=\"form-control\" rows=\"3\" id=\"Speciality\"></textarea>\n+    \t</div>\n+  \t</div>\n+  \t<!-- Experience -->\n+  \t<div class=\"form-group\">\n+  \t\t<label for=\"\" class=\"col-sm-2 col-sm-offset-2 control-label\">Experience</label>\n+    \t<div class=\"col-sm-5\">\n+      \t\t<textarea class=\"form-control\" rows=\"3\" id=\"\"></textarea>\n+    \t</div>\n+  \t</div>\n+  \t<!-- Button -->\n+  \t<div class=\"form-group\" style=\"margin-bottom: 0\">\n+    \t<div class=\"col-sm-offset-4 col-sm-5\">\n+      \t\t<button id=\"submit\" type=\"submit\" class=\"btn btn-success\">Submit</button>\n+      \t\t<button type=\"reset\" class=\"btn btn-info\">Reset</button>\n+    \t</div>\n+  \t</div>\n+</form>\n+<div style=\"height: 15px;background-color: #f5f5f5\"></div>\n+<footer>\n+  <div class=\"text-center\" style=\"background-color: #ddd;\">\n+      <a href=\"#\">Jiushig</a>&nbsp;&copy;&nbsp;<span><%=new Date()%></span>\n+  </div>\n+</footer>\n+</div>\n+<script src=\"http://cdn.bootcss.com/jquery/1.11.1/jquery.min.js\"></script>\n+<script src=\"http://cdn.bootcss.com/bootstrap/3.3.0/js/bootstrap.min.js\"></script>\n+</body>\n+</html>"
  }, {
    "sha" : "18dc8fc14c038843dd188490b4a1680b20c5df14",
    "filename" : "labs/1414080902139/inforeceive.jsp",
    "status" : "added",
    "additions" : 40,
    "deletions" : 0,
    "changes" : 40,
    "blob_url" : "https://github.com/hzuapps/java-web/blob/934e003eb507dc9457a49a03e994d83b6efdf18f/labs/1414080902139/inforeceive.jsp",
    "raw_url" : "https://github.com/hzuapps/java-web/raw/934e003eb507dc9457a49a03e994d83b6efdf18f/labs/1414080902139/inforeceive.jsp",
    "contents_url" : "https://api.github.com/repos/hzuapps/java-web/contents/labs/1414080902139/inforeceive.jsp?ref=934e003eb507dc9457a49a03e994d83b6efdf18f",
    "patch" : "@@ -0,0 +1,40 @@\n+<%@ page language=\"java\" import=\"java.util.*\" pageEncoding=\"utf-8\"%>\n+<%\n+String path = request.getContextPath();\n+String basePath = request.getScheme()+\"://\"+request.getServerName()+\":\"+request.getServerPort()+path+\"/\";\n+%>\n+<!DOCTYPE html>\n+<html lang=\"en\">\n+<head>\n+\t<base href=\"<%=basePath%>\">\n+\t<meta charset=\"UTF-8\">\n+\t<meta http-equiv=\"X-UA-Compatible\" content=\"IE=edge\">\n+    <meta name=\"viewport\" content=\"width=device-width, initial-scale=1\">\n+\t<title>Add Your Resume</title>\n+\t<link rel=\"stylesheet\" href=\"http://cdn.bootcss.com/bootstrap/3.3.0/css/bootstrap.min.css\">\n+\t<!-- HTML5 shim and Respond.js for IE8 support of HTML5 elements and media queries -->\n+    <!-- WARNING: Respond.js doesn't work if you view the page via file:// -->\n+    <!--[if lt IE 9]>\n+      \t<script src=\"http://cdn.bootcss.com/html5shiv/3.7.2/html5shiv.min.js\"></script>\n+      \t<script src=\"http://cdn.bootcss.com/respond.js/1.4.2/respond.min.js\"></script>\n+    <![endif]-->\n+\t<title>Document</title>\n+</head>\n+<body>\n+\t<% \trequest.setCharacterEncoding(\"UTF-8\");\n+\t\tString fullname=request.getParameter(\"fullnameinfo\");\n+\t%>\n+<div class=\"container\">\n+<form id=\"\" class=\"form-horizontal\" role=\"form\" style=\"background-color: #f5f5f5\">\n+\t<div class=\"text-center\" style=\"fone-family:微软雅黑;font-size:24px;height:45px;line-height:45px\"><%=fullname%>,welcome！</div>\n+</form>\n+<footer>\n+  <div class=\"text-center\" style=\"background-color: #ddd;\">\n+      <a href=\"#\">Jiushig</a>&nbsp;&copy;&nbsp;<span><%=new Date()%></span>\n+  </div>\n+</footer>\n+</div>\n+<script src=\"http://cdn.bootcss.com/jquery/1.11.1/jquery.min.js\"></script>\n+<script src=\"http://cdn.bootcss.com/bootstrap/3.3.0/js/bootstrap.min.js\"></script>\t\n+</body>\n+</html>\n\\ No newline at end of file"
  } ],
  "sha" : "934e003eb507dc9457a49a03e994d83b6efdf18f",
  "url" : "https://api.github.com/repos/hzuapps/java-web/commits/934e003eb507dc9457a49a03e994d83b6efdf18f",
  "parents" : [ {
    "sha" : "24f9e8cc824020d9e22a876c38b90a3ac19f227a",
    "url" : "https://api.github.com/repos/hzuapps/java-web/commits/24f9e8cc824020d9e22a876c38b90a3ac19f227a",
    "html_url" : "https://github.com/hzuapps/java-web/commit/24f9e8cc824020d9e22a876c38b90a3ac19f227a"
  } ]
}